dxcam_cpp/__init__.py
dxcam_cpp/dxcam_cpp.cp310-win_amd64.pyd
dxcam_cpp/opencv_core4.dll
dxcam_cpp/opencv_imgcodecs4.dll
dxcam_cpp/opencv_imgproc4.dll
dxcam_cpp/zlib1.dll
dxcam_cpp-0.2.5.dist-info/METADATA
dxcam_cpp-0.2.5.dist-info/WHEEL
dxcam_cpp-0.2.5.dist-info/licenses/LICENSE
dxcam_cpp-0.2.5.dist-info/RECORD
